{
  "ret": 200,
  "data": {
    "code": 0,
    "msg": "",
    "info": [
      {
        "recordcount": 35951,
        "result": [
          {
            "atypeName": "电视剧",
            "videoClassID": "0,1,4,133",
            "image": "https://static.yfsp.tv/upload/video/202503311441174174454.gif",
            "key": "oohvqiAeDaD",
            "lang": "韩语",
            "cid": "喜剧",
            "lastName": "12集全",
            "isShowTodayNum": false,
            "title": "离婚保险",
            "hot": 369329,
            "rating": "8.3",
            "year": 2025,
            "regional": "韩国",
            "addTime": "2025年03月31日",
            "directed": "李元锡",
            "starring": "李栋旭,李主傧,李光洙,李多熙",
            "shareCount": 45,
            "dd": 93,
            "dc": 19,
            "comments": 45,
            "favoriteCount": 788,
            "contxt": "一家保险公司的产品开发团队在开发一款与离婚相关的产品时发生的故事，通过制定保险金的过程回顾爱情、结婚、离婚等。",
            "isSerial": false,
            "updateweekly": "周一、周二",
            "cidMapper": "喜剧,爱情",
            "lastKey": "Xqz6Yz7DyoH1",
            "recommended": false,
            "updates": 0,
            "tags": null,
            "isFilm": false,
            "isDocumentry": false,
            "labels": "",
            "charge": 0,
            "vipResource": "1080P",
            "sNo": "",
            "serialCount": 0,
            "score": "8.3",
            "isFix": false
          },
          {
            "atypeName": "电视剧",
            "videoClassID": "0,1,4,152",
            "image": "https://static.yfsp.tv/upload/video/202503311359435966620.gif",
            "key": "t1sj3yIXom3",
            "lang": "日语",
            "cid": "剧情",
            "lastName": "87",
            "isShowTodayNum": true,
            "title": "红豆面包",
            "hot": 188943,
            "rating": "7.5",
            "year": 2025,
            "regional": "日本",
            "addTime": "2025年03月31日",
            "directed": "柳川强",
            "starring": "今田美樱,北村匠海,二宫和也,松岛菜菜子,加濑亮",
            "shareCount": 5,
            "dd": 18,
            "dc": 6,
            "comments": 16,
            "favoriteCount": 98,
            "contxt": "本剧以创作《面包超人》的柳濑嵩和小松畅夫妇为原型，以昭和初期为背景，横跨战前至战后，讲述了两人借由红豆面包结识，从失去生活意义的苦难岁月到不忘梦想的人生故事。在这个爱与勇气的物语中，这对曾经无名...",
            "isSerial": true,
            "updateweekly": "周一",
            "cidMapper": "剧情,历史",
            "lastKey": "QQJzT5KaI3S",
            "recommended": false,
            "updates": 1,
            "tags": null,
            "isFilm": false,
            "isDocumentry": false,
            "labels": "",
            "charge": 0,
            "vipResource": "1080P",
            "sNo": "",
            "serialCount": 0,
            "score": "6.0",
            "isFix": false
          },
          {
            "atypeName": "综艺",
            "videoClassID": "0,1,5,39",
            "image": "https://static.yfsp.tv/upload/video/202503301807560781506.gif",
            "key": "elS0Yzy8sQw",
            "lang": "韩语",
            "cid": "真人秀",
            "lastName": "10集全",
            "isShowTodayNum": false,
            "title": "爱德华李的乡村料理",
            "hot": 44171,
            "rating": "10.0",
            "year": 2025,
            "regional": "韩国",
            "addTime": "2025年03月30日",
            "directed": "",
            "starring": "爱德华·李,卞约汉,高我星,申诗雅",
            "shareCount": 3,
            "dd": 17,
            "dc": 0,
            "comments": 2,
            "favoriteCount": 77,
            "contxt": "讲述了厨师爱德华李寻找令人难以抗拒的多巴胺味道的旅程。 爱德华李和搭档女儿亚丁将作为特邀嘉宾，环游韩国，以各种概念呈现使用时令食材的菜肴。",
            "isSerial": false,
            "updateweekly": "周六",
            "cidMapper": "真人秀",
            "lastKey": "0HL91unWDD7",
            "recommended": false,
            "updates": 0,
            "tags": null,
            "isFilm": false,
            "isDocumentry": false,
            "labels": "",
            "charge": 0,
            "vipResource": "1080P",
            "sNo": "",
            "serialCount": 0,
            "score": "暂无评分",
            "isFix": false
          },
          {
            "atypeName": "电视剧",
            "videoClassID": "0,1,4,152",
            "image": "https://static.yfsp.tv/upload/video/202503301351175185088.gif",
            "key": "e71BXBoW3GA",
            "lang": "英语",
            "cid": "剧情",
            "lastName": "13集全",
            "isShowTodayNum": false,
            "title": "百变王牌第2季",
            "hot": 32457,
            "rating": "6.0",
            "year": 2025,
            "regional": "欧美",
            "addTime": "2025年03月30日",
            "directed": "",
            "starring": "嘉科莫·吉安尼欧缇,瓦妮莎·摩根",
            "shareCount": 3,
            "dd": 7,
            "dc": 2,
            "comments": 1,
            "favoriteCount": 65,
            "contxt": "带有喜剧色彩的悬疑破案程序剧，讲述科尔埃利斯是一名被降职的水警，他逮捕了一个女骗子麦克斯米切尔，在被拘留并被关押在警察局期间，米切尔帮助他侦破了另一起案件。两人获得了救赎的机会埃利斯有机会拿回他...",
            "isSerial": false,
            "updateweekly": "周日",
            "cidMapper": "剧情,罪案",
            "lastKey": "bbxRRgUfGD1",
            "recommended": false,
            "updates": 0,
            "tags": null,
            "isFilm": false,
            "isDocumentry": false,
            "labels": "",
            "charge": 0,
            "vipResource": "1080P",
            "sNo": "",
            "serialCount": 0,
            "score": "暂无评分",
            "isFix": false
          },
          {
            "atypeName": "电视剧",
            "videoClassID": "0,1,4,132",
            "image": "https://static.yfsp.tv/upload/video/202503301346144647821.gif",
            "key": "m2Kwlun3zIH",
            "lang": "国语",
            "cid": "都市",
            "lastName": "29集全",
            "isShowTodayNum": false,
            "title": "以美之名",
            "hot": 2091503,
            "rating": "8.7",
            "year": 2025,
            "regional": "大陆",
            "addTime": "2025年03月30日",
            "directed": "李少飞",
            "starring": "姚晨,贾静雯,侯雯元,袁弘,代乐乐",
            "shareCount": 116,
            "dd": 237,
            "dc": 35,
            "comments": 124,
            "favoriteCount": 1138,
            "contxt": "师出同门的整形外科医生乔杨和周静雯是多年冤家，两个女人在各自最糗的时刻迎来宿命般重逢，同为整形医院的王牌医生，二人带领各自团队，展开关于美、关于女性职场、关于医者仁心的激烈探讨与冲撞。直到更大的...",
            "isSerial": false,
            "updateweekly": "",
            "cidMapper": "都市,剧情",
            "lastKey": "GV1btYjxFEA",
            "recommended": false,
            "updates": 0,
            "tags": null,
            "isFilm": false,
            "isDocumentry": false,
            "labels": "",
            "charge": 0,
            "vipResource": "4K",
            "sNo": "",
            "serialCount": 0,
            "score": "8.7",
            "isFix": false
          },
          {
            "atypeName": "电视剧",
            "videoClassID": "0,1,4,130",
            "image": "https://static.yfsp.tv/upload/video/202503301329262957814.gif",
            "key": "QzWOksL3j3S",
            "lang": "国语",
            "cid": "家庭",
            "lastName": "36集全",
            "isShowTodayNum": false,
            "title": "我的后半生",
            "hot": 2568344,
            "rating": "7.3",
            "year": 2025,
            "regional": "大陆",
            "addTime": "2025年03月30日",
            "directed": "",
            "starring": "张国立,佟大为,梅婷,许娣,周野芒,杨童舒,严晓频,丁嘉丽,邬君梅,张丰毅,韩童生,牛飘,齐欢,沈佳妮,王真儿,郑卫莉,梁家桐",
            "shareCount": 107,
            "dd": 126,
            "dc": 46,
            "comments": 152,
            "favoriteCount": 711,
            "contxt": "沈卓然是已退休的文学系教授，儿女双全、三代同堂，发妻去世后他在老友的鼓励下开启了相亲之旅。他先后遇到了四位相亲对象。善解人意的护士长因房产与他分道扬镳；女科学家癌症复发选择了不告而别；工会主任的...",
            "isSerial": false,
            "updateweekly": "",
            "cidMapper": "家庭,都市,喜剧",
            "lastKey": "EpzHwzDexyS0",
            "recommended": false,
            "updates": 0,
            "tags": null,
            "isFilm": false,
            "isDocumentry": false,
            "labels": "",
            "charge": 0,
            "vipResource": "4K",
            "sNo": "",
            "serialCount": 0,
            "score": "7.3",
            "isFix": false
          },
          {
            "atypeName": "电视剧",
            "videoClassID": "0,1,4,152",
            "image": "https://static.yfsp.tv/upload/video/202503301135533573841.gif",
            "key": "Zx3BwTw40w5",
            "lang": "其它",
            "cid": "剧情",
            "lastName": "08集全",
            "isShowTodayNum": false,
            "title": "德黑兰第3季",
            "hot": 43907,
            "rating": "8.5",
            "year": 2024,
            "regional": "欧美",
            "addTime": "2025年03月30日",
            "directed": "",
            "starring": "妮芙·苏丹,肖恩·托布,达流士·胡马云,休·劳瑞,贝希·贾纳蒂·阿泰",
            "shareCount": 1,
            "dd": 22,
            "dc": 4,
            "comments": 5,
            "favoriteCount": 91,
            "contxt": "故事讲述以色列情报及特殊使命局（Mossad）一名女特务，乔装潜入伊朗首都德黑兰（Tehran）为进行一项危险任务的惊险过程。",
            "isSerial": false,
            "updateweekly": "周日",
            "cidMapper": "剧情,惊悚,动作",
            "lastKey": "ZFlOeT4BH6B",
            "recommended": false,
            "updates": 0,
            "tags": null,
            "isFilm": false,
            "isDocumentry": false,
            "labels": "",
            "charge": 0,
            "vipResource": "1080P",
            "sNo": "",
            "serialCount": 0,
            "score": "8.5",
            "isFix": false
          },
          {
            "atypeName": "电视剧",
            "videoClassID": "0,1,4,155",
            "image": "https://static.yfsp.tv/upload/video/202503300400160040315.gif",
            "key": "tkZVkBbtug8",
            "lang": "国语",
            "cid": "短剧",
            "lastName": "18集全",
            "isShowTodayNum": false,
            "title": "从天而降的幸运星",
            "hot": 40282,
            "rating": "7.5",
            "year": 2025,
            "regional": "大陆",
            "addTime": "2025年03月30日",
            "directed": "明昶",
            "starring": "任运杰,张心怡",
            "shareCount": 3,
            "dd": 9,
            "dc": 3,
            "comments": 0,
            "favoriteCount": 39,
            "contxt": "拥有幸运属性的土星人郝瑞池穿越来到了地球，遇上了不太走运的祁妙，两人展开了一段奇妙的爱情。",
            "isSerial": false,
            "updateweekly": "",
            "cidMapper": "短剧,都市,奇幻",
            "lastKey": "PzrdIHs7yNh",
            "recommended": false,
            "updates": 0,
            "tags": null,
            "isFilm": false,
            "isDocumentry": false,
            "labels": "",
            "charge": 0,
            "vipResource": "1080P",
            "sNo": "",
            "serialCount": 0,
            "score": "暂无评分",
            "isFix": false
          },
          {
            "atypeName": "电影",
            "videoClassID": "0,1,3,32",
            "image": "https://static.yfsp.tv/upload/video/202503291700580080081.gif",
            "key": "dzWFZuJWdkB",
            "lang": "英语",
            "cid": "悬疑",
            "lastName": "",
            "isShowTodayNum": false,
            "title": "珍妮潘的规则",
            "hot": 45996,
            "rating": "4.9",
            "year": 2024,
            "regional": "其它",
            "addTime": "2025年03月29日",
            "directed": "詹姆斯·阿什克罗夫特",
            "starring": "约翰·利思戈,杰弗里·拉什,纳撒尼尔·利斯,伊恩·穆内,托马斯·萨恩斯伯里",
            "shareCount": 32,
            "dd": 17,
            "dc": 18,
            "comments": 9,
            "favoriteCount": 43,
            "contxt": "斯蒂芬莫滕森（杰弗里拉什 饰）是一名老年法官，在一次近乎致命的中风导致他部分瘫痪后，他搬进了一家养老院。在那里，莫滕森与另一位居民发生了冲突，戴夫克里利（约翰利思戈 饰）有点不合群，他用一款名为...",
            "isSerial": false,
            "updateweekly": "",
            "cidMapper": "悬疑,惊悚,恐怖",
            "lastKey": "H9IuAyeB3z7",
            "recommended": false,
            "updates": 0,
            "tags": null,
            "isFilm": true,
            "isDocumentry": false,
            "labels": "",
            "charge": 0,
            "vipResource": "1080P",
            "sNo": "",
            "serialCount": 0,
            "score": "4.9",
            "isFix": false
          },
          {
            "atypeName": "综艺",
            "videoClassID": "0,1,5,39",
            "image": "https://static.yfsp.tv/upload/video/202503291626022678583.gif",
            "key": "BIRpyGlBen9",
            "lang": "国语",
            "cid": "真人秀",
            "lastName": "20250619(音你派对)集全",
            "isShowTodayNum": false,
            "title": "音你而来第2季",
            "hot": 284141,
            "rating": "9.0",
            "year": 2025,
            "regional": "大陆",
            "addTime": "2025年03月29日",
            "directed": "",
            "starring": "张震岳,张碧晨,武艺,王琳凯,欧阳娜娜,王赫野,陈卓璇",
            "shareCount": 17,
            "dd": 44,
            "dc": 5,
            "comments": 28,
            "favoriteCount": 198,
            "contxt": "游走大马街头，体验南洋文化，一切都是最美好的音乐旅行。",
            "isSerial": false,
            "updateweekly": "周四",
            "cidMapper": "真人秀",
            "lastKey": "slBXAWhhdj7",
            "recommended": false,
            "updates": 0,
            "tags": null,
            "isFilm": false,
            "isDocumentry": false,
            "labels": "",
            "charge": 0,
            "vipResource": "4K",
            "sNo": "",
            "serialCount": 0,
            "score": "9.0",
            "isFix": false
          },
          {
            "atypeName": "电视剧",
            "videoClassID": "0,1,4,133",
            "image": "https://static.yfsp.tv/upload/video/202503291310111088351.gif",
            "key": "wljC3mdN29C",
            "lang": "英语",
            "cid": "喜剧",
            "lastName": "06集全",
            "isShowTodayNum": false,
            "title": "大男孩第3季",
            "hot": 6578,
            "rating": "6.0",
            "year": 2025,
            "regional": "英国",
            "addTime": "2025年03月29日",
            "directed": "吉姆·阿切尔",
            "starring": "迪兰·卢埃林,乔纳森·珀恩廷,卡蜜尔·柯杜丽,卡蒂·威克斯,伊祖卡·霍伊尔",
            "shareCount": 1,
            "dd": 3,
            "dc": 3,
            "comments": 6,
            "favoriteCount": 11,
            "contxt": "在第三季中，伙伴们迎来了在Brent Uni的最后一年，经历了学位论文、最后期限、约会以及Louis Walsh离开《X-Factor》的打击（反正对杰克来说是这样！）等各种波折。",
            "isSerial": false,
            "updateweekly": "周六",
            "cidMapper": "喜剧",
            "lastKey": "EgVDMuyyycd0",
            "recommended": false,
            "updates": 0,
            "tags": null,
            "isFilm": false,
            "isDocumentry": false,
            "labels": "",
            "charge": 0,
            "vipResource": "1080P",
            "sNo": "",
            "serialCount": 0,
            "score": "暂无评分",
            "isFix": false
          },
          {
            "atypeName": "电视剧",
            "videoClassID": "0,1,4,132",
            "image": "https://static.yfsp.tv/upload/video/202503291300590047100.gif",
            "key": "cxPxLpGey31",
            "lang": "国语",
            "cid": "都市",
            "lastName": "32集全",
            "isShowTodayNum": false,
            "title": "有你的时光里",
            "hot": 850702,
            "rating": "6.4",
            "year": 2025,
            "regional": "大陆",
            "addTime": "2025年03月29日",
            "directed": "张胜富",
            "starring": "童瑶,周依然,李泽锋,张子贤,王劲松,刘丹",
            "shareCount": 51,
            "dd": 58,
            "dc": 32,
            "comments": 50,
            "favoriteCount": 442,
            "contxt": "《有你的时光里》讲述事业全能、雷厉风行的都市女强人姐姐王焱（童瑶 饰）和“一身傲骨”硬闯深圳的叛逆妹妹王灵均（周依然 饰）二人共同在大城市经历职场风波、恋情纠葛后放下内心芥蒂重新审视自我，最终实...",
            "isSerial": false,
            "updateweekly": "",
            "cidMapper": "都市,电视剧",
            "lastKey": "dUCaq0L8AGC",
            "recommended": false,
            "updates": 0,
            "tags": null,
            "isFilm": false,
            "isDocumentry": false,
            "labels": "",
            "charge": 0,
            "vipResource": "1080P",
            "sNo": "",
            "serialCount": 0,
            "score": "6.7",
            "isFix": false
          },
          {
            "atypeName": "电视剧",
            "videoClassID": "0,1,4,152",
            "image": "https://static.yfsp.tv/upload/video/202503291125232546242.gif",
            "key": "pDXTUU1Xn85",
            "lang": "英语",
            "cid": "剧情",
            "lastName": "08集全",
            "isShowTodayNum": false,
            "title": "胖者生存第2季",
            "hot": 15659,
            "rating": "6.0",
            "year": 2025,
            "regional": "欧美",
            "addTime": "2025年03月29日",
            "directed": "",
            "starring": "丹·安博尔,德翁·科尔",
            "shareCount": 0,
            "dd": 3,
            "dc": 5,
            "comments": 1,
            "favoriteCount": 25,
            "contxt": "惨痛分手后，热情洋溢的造型师梅维斯博蒙特把握机会整顿生活、重新追求爱情，要用自己的方式找到快乐。",
            "isSerial": false,
            "updateweekly": "周六",
            "cidMapper": "喜剧",
            "lastKey": "92lFDMzNDsP",
            "recommended": false,
            "updates": 0,
            "tags": null,
            "isFilm": false,
            "isDocumentry": false,
            "labels": "",
            "charge": 0,
            "vipResource": "1080P",
            "sNo": "",
            "serialCount": 0,
            "score": "暂无评分",
            "isFix": false
          },
          {
            "atypeName": "电视剧",
            "videoClassID": "0,1,4,133",
            "image": "https://static.yfsp.tv/upload/video/202503281709590916785.gif",
            "key": "VQtSKV5DkfE",
            "lang": "英语",
            "cid": "喜剧",
            "lastName": "10集全",
            "isShowTodayNum": false,
            "title": "中世纪摩登",
            "hot": 40572,
            "rating": "8.6",
            "year": 2025,
            "regional": "欧美",
            "addTime": "2025年03月28日",
            "directed": "瑞恩·墨菲",
            "starring": "马特·波莫,内森·连恩,琳达·拉文,内森·李·格雷厄姆,克林顿·路比",
            "shareCount": 6,
            "dd": 32,
            "dc": 5,
            "comments": 13,
            "favoriteCount": 128,
            "contxt": "该剧由Ryan Murphy执导，背景设定在同志天堂棕榈泉，剧情类似现代版《黄金女郎》，Matt和Nathan将饰演一对同志室友，角色设定类似于《黄金女郎》中的Rose和Dorothy。",
            "isSerial": false,
            "updateweekly": "周五",
            "cidMapper": "喜剧,同性",
            "lastKey": "K5M0cRcYWY5",
            "recommended": false,
            "updates": 0,
            "tags": null,
            "isFilm": false,
            "isDocumentry": false,
            "labels": "",
            "charge": 0,
            "vipResource": "1080P",
            "sNo": "",
            "serialCount": 0,
            "score": "8.6",
            "isFix": false
          },
          {
            "atypeName": "电视剧",
            "videoClassID": "0,1,4,150",
            "image": "https://static.yfsp.tv/upload/video/202503281654215420446.gif",
            "key": "9WurhFFzar5",
            "lang": "英语",
            "cid": "动作",
            "lastName": "10",
            "isShowTodayNum": false,
            "title": "警戒：失踪人口调查组第3季",
            "hot": 39606,
            "rating": "6.0",
            "year": 2025,
            "regional": "欧美",
            "addTime": "2025年03月28日",
            "directed": "",
            "starring": "斯科特·凯恩,丹妮亚·拉米雷兹",
            "shareCount": 2,
            "dd": 2,
            "dc": 4,
            "comments": 5,
            "favoriteCount": 86,
            "contxt": "跟随妮基帕克加入洛杉矶警察局的失踪人员调查组，在她寻找失踪儿子的同时帮助其他人找到他们所爱的人。",
            "isSerial": true,
            "updateweekly": "周五",
            "cidMapper": "动作,悬疑,惊悚",
            "lastKey": "2uBq4za0xHA",
            "recommended": false,
            "updates": 0,
            "tags": null,
            "isFilm": false,
            "isDocumentry": false,
            "labels": "",
            "charge": 0,
            "vipResource": "1080P",
            "sNo": "",
            "serialCount": 0,
            "score": "暂无评分",
            "isFix": false
          },
          {
            "atypeName": "电视剧",
            "videoClassID": "0,1,4,152",
            "image": "https://static.yfsp.tv/upload/video/202403071326452624027.gif",
            "key": "nQHRiqp5CCA",
            "lang": "英语",
            "cid": "剧情",
            "lastName": "12集全",
            "isShowTodayNum": false,
            "title": "清洁工第4季",
            "hot": 66392,
            "rating": "3.8",
            "year": 2025,
            "regional": "欧美",
            "addTime": "2025年03月28日",
            "directed": "",
            "starring": "艾洛蒂·袁",
            "shareCount": 1,
            "dd": 6,
            "dc": 10,
            "comments": 7,
            "favoriteCount": 136,
            "contxt": "剧中讲述女主是个机智的医生，她来到美国寻求医治生病儿子的方法，然而美国却逼使她躲起来不过她决心不会就此屈服，并转而投向黑帮当起解决问题的「清洁工」。",
            "isSerial": false,
            "updateweekly": "周五",
            "cidMapper": "剧情,罪案",
            "lastKey": "YeD233wFZM3",
            "recommended": false,
            "updates": 0,
            "tags": null,
            "isFilm": false,
            "isDocumentry": false,
            "labels": "",
            "charge": 0,
            "vipResource": "1080P",
            "sNo": "",
            "serialCount": 0,
            "score": "暂无评分",
            "isFix": false
          },
          {
            "atypeName": "电影",
            "videoClassID": "0,1,3,19",
            "image": "https://static.yfsp.tv/upload/video/202503281212431266274.gif",
            "key": "pxGleaTjLWC",
            "lang": "英语",
            "cid": "喜剧",
            "lastName": "",
            "isShowTodayNum": false,
            "title": "亚历山大和他最糟糕的旅程",
            "hot": 24008,
            "rating": "4.4",
            "year": 2025,
            "regional": "其它",
            "addTime": "2025年03月28日",
            "directed": "马文·莱穆斯",
            "starring": "伊娃·朗格利亚,杰西·加西亚,宝琳娜·查韦斯,罗斯·波尔蒂略,托姆·纳美尔",
            "shareCount": 22,
            "dd": 8,
            "dc": 10,
            "comments": 8,
            "favoriteCount": 29,
            "contxt": "你对全家出游的容忍度有多高？ 　　亚历山大家族踏上堪称史诗级灾难的溯源之旅，一切只因为某人身上受到了诅咒",
            "isSerial": false,
            "updateweekly": "",
            "cidMapper": "喜剧",
            "lastKey": "6ohfGBog5i0",
            "recommended": false,
            "updates": 0,
            "tags": null,
            "isFilm": true,
            "isDocumentry": false,
            "labels": "",
            "charge": 0,
            "vipResource": "1080P",
            "sNo": "",
            "serialCount": 0,
            "score": "5.1",
            "isFix": false
          },
          {
            "atypeName": "综艺",
            "videoClassID": "0,1,5,39",
            "image": "https://static.yfsp.tv/upload/video/202503281156325631181.gif",
            "key": "8gsIkt0wJ2C",
            "lang": "韩语",
            "cid": "真人秀",
            "lastName": "09",
            "isShowTodayNum": false,
            "title": "睁眼一看",
            "hot": 70283,
            "rating": "9.6",
            "year": 2025,
            "regional": "韩国",
            "addTime": "2025年03月28日",
            "directed": "",
            "starring": "朴正洙,金希澈,金钟云,申东熙,李赫宰",
            "shareCount": 12,
            "dd": 26,
            "dc": 1,
            "comments": 7,
            "favoriteCount": 128,
            "contxt": "SUPER JUNIOR即将开启出道20周年企划旅程，并以全新真人秀综艺《睁眼一看是 SUPER TV》拉开序幕，该综艺是一档为SUPER JUNIOR量身打造、独一无二的硬核综艺，步入成熟20...",
            "isSerial": true,
            "updateweekly": "周五",
            "cidMapper": "真人秀",
            "lastKey": "yeUjhwkQRE2",
            "recommended": false,
            "updates": 0,
            "tags": null,
            "isFilm": false,
            "isDocumentry": false,
            "labels": "",
            "charge": 0,
            "vipResource": "1080P",
            "sNo": "",
            "serialCount": 0,
            "score": "9.3",
            "isFix": false
          },
          {
            "atypeName": "电影",
            "videoClassID": "0,1,3,28",
            "image": "https://static.yfsp.tv/upload/video/202503281152505267238.gif",
            "key": "0EKsNP3qju4",
            "lang": "英语",
            "cid": "剧情",
            "lastName": "",
            "isShowTodayNum": false,
            "title": "生命清单",
            "hot": 67170,
            "rating": "7.2",
            "year": 2025,
            "regional": "欧美",
            "addTime": "2025年03月28日",
            "directed": "亚当·布鲁克斯",
            "starring": "索菲亚·卡尔森,凯尔·艾伦,塞巴斯蒂安·德·索萨,康妮·布里顿,何塞·祖尼加",
            "shareCount": 18,
            "dd": 31,
            "dc": 12,
            "comments": 15,
            "favoriteCount": 132,
            "contxt": "亚历克斯罗斯的母亲让她去完成童年的愿望清单时，她随之踏上了一段让人笑中带泪的旅程，并将在旅程中揭开家族秘密，收获爱情，并找到真正的自我。",
            "isSerial": false,
            "updateweekly": "",
            "cidMapper": "剧情,喜剧,爱情",
            "lastKey": "w0pqk6pf8z8",
            "recommended": false,
            "updates": 0,
            "tags": null,
            "isFilm": true,
            "isDocumentry": false,
            "labels": "",
            "charge": 0,
            "vipResource": "1080P",
            "sNo": "",
            "serialCount": 0,
            "score": "7.0",
            "isFix": false
          },
          {
            "atypeName": "电影",
            "videoClassID": "0,1,3,21",
            "image": "https://static.yfsp.tv/upload/video/202503281150045045821.gif",
            "key": "0wH6MWBl3mF",
            "lang": "法语",
            "cid": "动作",
            "lastName": "",
            "isShowTodayNum": false,
            "title": "劫车王",
            "hot": 59718,
            "rating": "3.5",
            "year": 2025,
            "regional": "欧美",
            "addTime": "2025年03月28日",
            "directed": "卡梅尔·吉姆拉",
            "starring": "弗兰克·盖思堂彼得,佐伊·马奇尔,Bosh",
            "shareCount": 15,
            "dd": 9,
            "dc": 17,
            "comments": 7,
            "favoriteCount": 80,
            "contxt": "白天，他们是隐形的豪华酒店的服务员、女招待和调酒师。到了晚上，他们就是劫车者，一群熟练的司机，在路上追踪和抢劫富有的客户。当他们计划最终的抢劫时，酒店经理雇佣了一名无情的杀手，不惜一切代价阻止他...",
            "isSerial": false,
            "updateweekly": "",
            "cidMapper": "动作",
            "lastKey": "xGTFCaFHny7",
            "recommended": false,
            "updates": 0,
            "tags": null,
            "isFilm": true,
            "isDocumentry": false,
            "labels": "",
            "charge": 0,
            "vipResource": "1080P",
            "sNo": "",
            "serialCount": 0,
            "score": "3.5",
            "isFix": false
          },
          {
            "atypeName": "电视剧",
            "videoClassID": "0,1,4,155",
            "image": "https://static.yfsp.tv/upload/video/202503281142064257831.gif",
            "key": "WXZ8cPwt616",
            "lang": "国语",
            "cid": "短剧",
            "lastName": "24集全",
            "isShowTodayNum": false,
            "title": "火舞倾城",
            "hot": 207457,
            "rating": "8.0",
            "year": 2025,
            "regional": "大陆",
            "addTime": "2025年03月28日",
            "directed": "潘嬿茜",
            "starring": "完颜洛绒,钟丽丽,郑繁星,展轩,余璐娜",
            "shareCount": 7,
            "dd": 41,
            "dc": 10,
            "comments": 33,
            "favoriteCount": 212,
            "contxt": "中学教师赵星柔与军阀少帅易秋霆相爱，却因家庭门第的差距遭到阻挠，易秋霆的强硬手段更是造成感情错位。赵星柔在以为失去孩子后假死离开，多年后她涅槃归来，用行动证明女性亦能以独立人格活出生命的光彩。",
            "isSerial": false,
            "updateweekly": "",
            "cidMapper": "短剧,剧情,爱情",
            "lastKey": "sYrwtVPvbL0",
            "recommended": false,
            "updates": 0,
            "tags": null,
            "isFilm": false,
            "isDocumentry": false,
            "labels": "",
            "charge": 0,
            "vipResource": "4K",
            "sNo": "",
            "serialCount": 0,
            "score": "8.0",
            "isFix": false
          },
          {
            "atypeName": "电影",
            "videoClassID": "0,1,3,26",
            "image": "https://static.yfsp.tv/upload/video/202503280903040300757.gif",
            "key": "xZySN2hkjL0",
            "lang": "粤语",
            "cid": "灾难",
            "lastName": "",
            "isShowTodayNum": false,
            "title": "焚城(粤语)",
            "hot": 435841,
            "rating": "9.2",
            "year": 2024,
            "regional": "香港",
            "addTime": "2025年03月28日",
            "directed": "潘耀明",
            "starring": "刘德华,白宇,莫文蔚,谢君豪,王菀之",
            "shareCount": 270,
            "dd": 307,
            "dc": 25,
            "comments": 89,
            "favoriteCount": 692,
            "contxt": "危险物质突发泄漏！24小时后危及香港全城。 　　如何及时阻止这场末日灾难，专家范伟立（刘德华 饰）与Cecilia（莫文蔚 饰）各执一词。同时，消防队长黎杰峰（白宇 饰）和队友已奉命奔赴未知前线...",
            "isSerial": false,
            "updateweekly": "",
            "cidMapper": "灾难,动作,剧情",
            "lastKey": "INArSDp3idE",
            "recommended": false,
            "updates": 0,
            "tags": null,
            "isFilm": true,
            "isDocumentry": false,
            "labels": "",
            "charge": 0,
            "vipResource": "4K",
            "sNo": "",
            "serialCount": 0,
            "score": "8.2",
            "isFix": false
          },
          {
            "atypeName": "电影",
            "videoClassID": "0,1,3,26",
            "image": "https://static.yfsp.tv/upload/video/202503280903040300757.gif",
            "key": "1Zc0M4DIz9H",
            "lang": "国语",
            "cid": "灾难",
            "lastName": "",
            "isShowTodayNum": false,
            "title": "焚城",
            "hot": 583721,
            "rating": "8.2",
            "year": 2024,
            "regional": "香港",
            "addTime": "2025年03月28日",
            "directed": "潘耀明",
            "starring": "刘德华,白宇,莫文蔚,谢君豪,王菀之",
            "shareCount": 470,
            "dd": 256,
            "dc": 55,
            "comments": 114,
            "favoriteCount": 907,
            "contxt": "危险物质突发泄漏！24小时后危及香港全城。 　　如何及时阻止这场末日灾难，专家范伟立（刘德华 饰）与Cecilia（莫文蔚 饰）各执一词。同时，消防队长黎杰峰（白宇 饰）和队友已奉命奔赴未知前线...",
            "isSerial": false,
            "updateweekly": "",
            "cidMapper": "灾难,动作,剧情",
            "lastKey": "cCjOHiK1ffC",
            "recommended": false,
            "updates": 0,
            "tags": null,
            "isFilm": true,
            "isDocumentry": false,
            "labels": "",
            "charge": 0,
            "vipResource": "4K",
            "sNo": "",
            "serialCount": 0,
            "score": "7.7",
            "isFix": false
          },
          {
            "atypeName": "电视剧",
            "videoClassID": "0,1,4,152",
            "image": "https://static.yfsp.tv/upload/video/202503280613541374705.gif",
            "key": "qAjXYQVldtB",
            "lang": "国语",
            "cid": "剧情",
            "lastName": "12集全",
            "isShowTodayNum": false,
            "title": "沙尘暴",
            "hot": 1717256,
            "rating": "9.4",
            "year": 2025,
            "regional": "大陆",
            "addTime": "2025年03月28日",
            "directed": "谭嘉言",
            "starring": "段奕宏,王锵,张佳宁,张瑶,杨新鸣",
            "shareCount": 99,
            "dd": 494,
            "dc": 33,
            "comments": 346,
            "favoriteCount": 1486,
            "contxt": "一桩焚尸旧案被重查，基层民警陈江河（段奕宏 饰）也被紧急调回。当他再次进入小城，搅局的骗子、撒谎的真凶、复仇的牺牲者，犹如一场沙尘暴将他笼罩其中。但他坚信罪恶皆有源，再大的风暴也终会平息，天地总...",
            "isSerial": false,
            "updateweekly": "",
            "cidMapper": "剧情,悬疑",
            "lastKey": "CbeIewmlmK8",
            "recommended": false,
            "updates": 0,
            "tags": null,
            "isFilm": false,
            "isDocumentry": false,
            "labels": "",
            "charge": 0,
            "vipResource": "4K",
            "sNo": "",
            "serialCount": 0,
            "score": "8.7",
            "isFix": false
          },
          {
            "atypeName": "电视剧",
            "videoClassID": "0,1,4,155",
            "image": "https://static.yfsp.tv/upload/video/202503280500060015062.gif",
            "key": "mjj0DhYdUr5",
            "lang": "国语",
            "cid": "短剧",
            "lastName": "24集全",
            "isShowTodayNum": false,
            "title": "宫墙厌",
            "hot": 233884,
            "rating": "7.4",
            "year": 2025,
            "regional": "大陆",
            "addTime": "2025年03月28日",
            "directed": "",
            "starring": "何宣林,程宇峰,王星凯",
            "shareCount": 35,
            "dd": 35,
            "dc": 12,
            "comments": 17,
            "favoriteCount": 192,
            "contxt": "替嫁杀手地十七伪装成和亲公主入宫行刺，阴差阳错间与五皇子欧阳绍相识相爱。杀手主人却以家人相挟，逼地十七取五皇子性命。必须践行的使命，无法拒绝的爱情，两难抉择之下，两人携手砥砺前行，只为一刻相守。",
            "isSerial": false,
            "updateweekly": "",
            "cidMapper": "短剧,爱情,古装",
            "lastKey": "zc4zycrs0wq0",
            "recommended": false,
            "updates": 0,
            "tags": null,
            "isFilm": false,
            "isDocumentry": false,
            "labels": "",
            "charge": 0,
            "vipResource": "4K",
            "sNo": "",
            "serialCount": 0,
            "score": "7.4",
            "isFix": false
          },
          {
            "atypeName": "电视剧",
            "videoClassID": "0,1,4,155",
            "image": "https://static.yfsp.tv/upload/video/202503280437043727670.gif",
            "key": "dHq8Nzly4Dd",
            "lang": "国语",
            "cid": "短剧",
            "lastName": "24集全",
            "isShowTodayNum": false,
            "title": "白事先生",
            "hot": 42181,
            "rating": "7.4",
            "year": 2025,
            "regional": "大陆",
            "addTime": "2025年03月28日",
            "directed": "殷博",
            "starring": "史元庭,王馨伟,王岗,李源冰,王毅凡",
            "shareCount": 0,
            "dd": 29,
            "dc": 10,
            "comments": 7,
            "favoriteCount": 44,
            "contxt": "本故事讲述了顺喜在一次次白事委托中，渐渐成长为一名优秀的白事先生。他也终于明白了身为白事先生的真正意义，为逝者哀悼，让生者释怀。故事聚焦殡葬题材，生老病死乃人之常情，白事是对死者最后关怀，于其本...",
            "isSerial": false,
            "updateweekly": "",
            "cidMapper": "短剧,家庭",
            "lastKey": "2dgAoCOYMLC",
            "recommended": false,
            "updates": 0,
            "tags": null,
            "isFilm": false,
            "isDocumentry": false,
            "labels": "",
            "charge": 0,
            "vipResource": "4K",
            "sNo": "",
            "serialCount": 0,
            "score": "7.4",
            "isFix": false
          },
          {
            "atypeName": "电视剧",
            "videoClassID": "0,1,4,152",
            "image": "https://static.yfsp.tv/upload/video/202503271909470903357.gif",
            "key": "PwrbS8o5h0A",
            "lang": "英语",
            "cid": "剧情",
            "lastName": "10集全",
            "isShowTodayNum": false,
            "title": "博斯：传承第3季",
            "hot": 49939,
            "rating": "9.4",
            "year": 2025,
            "regional": "欧美",
            "addTime": "2025年03月27日",
            "directed": "",
            "starring": "提图斯·维里沃",
            "shareCount": 4,
            "dd": 33,
            "dc": 2,
            "comments": 9,
            "favoriteCount": 103,
            "contxt": "博世开始了他职业生涯的下一个篇章，发现自己与他曾经的敌人哈尼钱德勒（Honey Chandler）共事。",
            "isSerial": false,
            "updateweekly": "周四",
            "cidMapper": "剧情,罪案",
            "lastKey": "jyyzCgeFIxh1",
            "recommended": false,
            "updates": 0,
            "tags": null,
            "isFilm": false,
            "isDocumentry": false,
            "labels": "",
            "charge": 0,
            "vipResource": "1080P",
            "sNo": "",
            "serialCount": 0,
            "score": "9.4",
            "isFix": false
          },
          {
            "atypeName": "电影",
            "videoClassID": "0,1,3,123",
            "image": "https://static.yfsp.tv/upload/video/202503271320182015347.gif",
            "key": "vVOM7Auafo2",
            "lang": "英语",
            "cid": "恐怖",
            "lastName": "",
            "isShowTodayNum": false,
            "title": "怪猴",
            "hot": 86530,
            "rating": "5.3",
            "year": 2025,
            "regional": "欧美",
            "addTime": "2025年03月27日",
            "directed": "奥斯古德·珀金斯",
            "starring": "西奥·詹姆斯,塔提阿娜·玛斯拉尼,伊利亚·伍德,劳拉·门内尔,克里斯蒂安·康佛瑞",
            "shareCount": 39,
            "dd": 46,
            "dc": 40,
            "comments": 42,
            "favoriteCount": 197,
            "contxt": "当双胞胎兄弟哈尔和比尔在阁楼上发现父亲的旧猴子玩具之后，他们周围开始发生一系列可怕的死亡事件。兄弟俩决定把猴子扔掉，继续他们的生活，但多年来却越来越疏远。但当神秘的死亡再次开始时，兄弟俩必须重新...",
            "isSerial": false,
            "updateweekly": "",
            "cidMapper": "恐怖",
            "lastKey": "XzOB6JCqAwT",
            "recommended": false,
            "updates": 0,
            "tags": null,
            "isFilm": true,
            "isDocumentry": false,
            "labels": "",
            "charge": 0,
            "vipResource": "1080P",
            "sNo": "",
            "serialCount": 0,
            "score": "5.3",
            "isFix": false
          },
          {
            "atypeName": "电影",
            "videoClassID": "0,1,3,27",
            "image": "https://static.yfsp.tv/upload/video/202503271243564318778.gif",
            "key": "3b15lKrSLK1",
            "lang": "英语",
            "cid": "惊悚",
            "lastName": "",
            "isShowTodayNum": false,
            "title": "荷兰镇",
            "hot": 64686,
            "rating": "3.3",
            "year": 2025,
            "regional": "欧美",
            "addTime": "2025年03月27日",
            "directed": "米米·凯夫",
            "starring": "妮可·基德曼,盖尔·加西亚·贝纳尔,马修·麦克费登,裘德·希尔,杰夫·波普",
            "shareCount": 17,
            "dd": 18,
            "dc": 37,
            "comments": 21,
            "favoriteCount": 142,
            "contxt": "密歇根州荷兰镇教师南希范德格鲁特（妮可基德曼 饰），她与担任社区领袖的丈夫弗雷德（马修麦克费登 饰）、儿子哈里过着典型的美国田园生活。当南希与同事戴夫德尔加多（盖尔加西亚贝纳尔 饰）偶然发现丈夫...",
            "isSerial": false,
            "updateweekly": "",
            "cidMapper": "惊悚",
            "lastKey": "c3iGQYPs0zB",
            "recommended": false,
            "updates": 0,
            "tags": null,
            "isFilm": true,
            "isDocumentry": false,
            "labels": "",
            "charge": 0,
            "vipResource": "1080P",
            "sNo": "",
            "serialCount": 0,
            "score": "3.3",
            "isFix": false
          },
          {
            "atypeName": "电影",
            "videoClassID": "0,1,3,19",
            "image": "https://static.yfsp.tv/upload/video/202503271243024341056.gif",
            "key": "6iOJ0uzOGfE",
            "lang": "国语",
            "cid": "喜剧",
            "lastName": "",
            "isShowTodayNum": false,
            "title": "诡才之道",
            "hot": 482238,
            "rating": "9.2",
            "year": 2024,
            "regional": "台湾",
            "addTime": "2025年03月27日",
            "directed": "徐汉强",
            "starring": "陈柏霖,张榕容,王净,姚以缇,百白,瘦瘦,罗芽里,葛凡,那维勋,叶静涵,赖雨霏,黄迪扬,林鹤轩,龙龙,昶玮,尹宣方,张承贤,赖玟君,黄豪平,吴志庆,杨达敬,洪藜恩,罗香菱,曹瑜,李进中,陈葳,蔡邵桓,苏耀庭,舒伟杰,贺珑,董芷涵",
            "shareCount": 279,
            "dd": 506,
            "dc": 44,
            "comments": 170,
            "favoriteCount": 1022,
            "contxt": "所有人都只关心闹鬼吓不吓人，却没人关心鬼闹得累不累。在著名闹鬼圣地旺来温泉大饭店414号房里，过气女鬼天后「凯萨琳」（张榕容 饰）和三流阴间经纪人「Makoto」（陈柏霖 饰）正在为培养菜鸟新鬼...",
            "isSerial": false,
            "updateweekly": "",
            "cidMapper": "喜剧,恐怖",
            "lastKey": "pb35avxFRUA",
            "recommended": false,
            "updates": 0,
            "tags": null,
            "isFilm": true,
            "isDocumentry": false,
            "labels": "",
            "charge": 0,
            "vipResource": "1080P",
            "sNo": "",
            "serialCount": 0,
            "score": "9.2",
            "isFix": false
          },
          {
            "atypeName": "纪录片",
            "videoClassID": "0,1,7,67",
            "image": "https://static.yfsp.tv/upload/video/202503271237213703652.gif",
            "key": "W3kDzSPEEHE",
            "lang": "英语",
            "cid": "其它",
            "lastName": "03集全",
            "isShowTodayNum": false,
            "title": "贪金之人：追寻古董富商的秘宝",
            "hot": 9619,
            "rating": "6.0",
            "year": 2025,
            "regional": "欧美",
            "addTime": "2025年03月27日",
            "directed": "",
            "starring": "",
            "shareCount": 0,
            "dd": 4,
            "dc": 0,
            "comments": 2,
            "favoriteCount": 20,
            "contxt": "名为福里斯特芬恩的古怪男子将一箱黄金藏在了落基山脉，并在一首隐晦的诗中留下线索，一场现实世界中的寻宝之旅就此展开。",
            "isSerial": false,
            "updateweekly": "周四",
            "cidMapper": "其它,探索",
            "lastKey": "QqzASRp63NN",
            "recommended": false,
            "updates": 0,
            "tags": null,
            "isFilm": false,
            "isDocumentry": true,
            "labels": "",
            "charge": 0,
            "vipResource": "1080P",
            "sNo": "",
            "serialCount": 0,
            "score": "暂无评分",
            "isFix": false
          },
          {
            "atypeName": "纪录片",
            "videoClassID": "0,1,7,50",
            "image": "https://static.yfsp.tv/upload/video/202503271228302883781.gif",
            "key": "iOHOMz9dyBY",
            "lang": "国语",
            "cid": "文化",
            "lastName": "06集全",
            "isShowTodayNum": false,
            "title": "牛奶是部文明史",
            "hot": 12604,
            "rating": "6.0",
            "year": 2025,
            "regional": "大陆",
            "addTime": "2025年03月27日",
            "directed": "陈晓卿 / 陈磊 / 邓洁",
            "starring": "",
            "shareCount": 0,
            "dd": 5,
            "dc": 0,
            "comments": 0,
            "favoriteCount": 40,
            "contxt": "首部聚焦牛奶的大型美食人文纪录片，深入探讨牛奶在人类历史与文化中的重要地位。通过科学知识、生动故事和真实情感，展现牛奶的营养、美味及其对人类生活的深远影响，揭示其在不同文化中的独特价值和意义。",
            "isSerial": false,
            "updateweekly": "周四",
            "cidMapper": "文化,其它",
            "lastKey": "fyo0UBlUXJD",
            "recommended": false,
            "updates": 0,
            "tags": null,
            "isFilm": false,
            "isDocumentry": true,
            "labels": "",
            "charge": 0,
            "vipResource": "4K",
            "sNo": "",
            "serialCount": 0,
            "score": "暂无评分",
            "isFix": false
          },
          {
            "atypeName": "电视剧",
            "videoClassID": "0,1,4,126",
            "image": "https://static.yfsp.tv/upload/video/202503271203540387071.gif",
            "key": "y8frC7M4yT5",
            "lang": "国语",
            "cid": "古装",
            "lastName": "30集全",
            "isShowTodayNum": false,
            "title": "念无双",
            "hot": 3229059,
            "rating": "8.8",
            "year": 2025,
            "regional": "大陆",
            "addTime": "2025年03月27日",
            "directed": "郭虎",
            "starring": "唐嫣,刘学义,郭晓婷,王弘毅,周柯宇,张俪,陈楚河,郑希怡,白澍,郑业成,马启越,修庆,郑国霖,傅淼,杨肸子,曾淇,丁嘉文,李泊文,朱戬",
            "shareCount": 226,
            "dd": 663,
            "dc": 92,
            "comments": 640,
            "favoriteCount": 1589,
            "contxt": "神魔大战，源生天神泰和利用神器神之左手封印魔神，神之左手被斩断坠落人界，泰和与众神陷人长眠，自此人界再无神迹。战鬼族趁乱崛起，引发大战，有狐族源仲得神之左手，打败战鬼族，再创休明盛世。自此有狐族...",
            "isSerial": false,
            "updateweekly": "",
            "cidMapper": "古装,爱情",
            "lastKey": "14KTGg5oCK8",
            "recommended": false,
            "updates": 0,
            "tags": null,
            "isFilm": false,
            "isDocumentry": false,
            "labels": "",
            "charge": 0,
            "vipResource": "4K",
            "sNo": "",
            "serialCount": 0,
            "score": "7.8",
            "isFix": false
          },
          {
            "atypeName": "电视剧",
            "videoClassID": "0,1,4,135",
            "image": "https://static.yfsp.tv/upload/video/202503270501180163134.gif",
            "key": "bxLsDbeDrf9",
            "lang": "国语",
            "cid": "军旅",
            "lastName": "24集全",
            "isShowTodayNum": false,
            "title": "女巡特警之蜂鸟突击队",
            "hot": 231131,
            "rating": "6.4",
            "year": 2025,
            "regional": "大陆",
            "addTime": "2025年03月27日",
            "directed": "",
            "starring": "程愫,蒋璐霞,杨杏,赵志瑶,李羽桐,魏一,徐洪浩,赵荀",
            "shareCount": 16,
            "dd": 30,
            "dc": 17,
            "comments": 18,
            "favoriteCount": 172,
            "contxt": "讲述了一系列滨江市特警支队蜂鸟小队打击违法犯罪，守护群众安宁的故事。蜂鸟小队是一群具有现代执法意识和能力的精英警察，他们富有人情味，充满信念感，在社区、在街头、在抓捕中、在没有硝烟却有牺牲的执法...",
            "isSerial": false,
            "updateweekly": "",
            "cidMapper": "军旅,警匪",
            "lastKey": "b6xUDzld6NP",
            "recommended": false,
            "updates": 0,
            "tags": null,
            "isFilm": false,
            "isDocumentry": false,
            "labels": "",
            "charge": 0,
            "vipResource": "4K",
            "sNo": "",
            "serialCount": 0,
            "score": "6.4",
            "isFix": false
          },
          {
            "atypeName": "电视剧",
            "videoClassID": "0,1,4,155",
            "image": "https://static.yfsp.tv/upload/video/202503270259235943366.gif",
            "key": "qAi75w0naTD",
            "lang": "国语",
            "cid": "短剧",
            "lastName": "24集全",
            "isShowTodayNum": false,
            "title": "锦月藏心",
            "hot": 60562,
            "rating": "6.0",
            "year": 2025,
            "regional": "大陆",
            "addTime": "2025年03月27日",
            "directed": "慕白",
            "starring": "韩东霖,何适",
            "shareCount": 2,
            "dd": 8,
            "dc": 1,
            "comments": 1,
            "favoriteCount": 41,
            "contxt": "《锦月藏心》以民国时期为背景，讲述了洛城四大家族之一的叶家千金叶晓斐和为复仇隐姓埋名的男主林青携手对抗四大家族，在合作中两人逐渐放下彼此的猜忌并暗生情愫的故事。",
            "isSerial": false,
            "updateweekly": "",
            "cidMapper": "短剧,言情",
            "lastKey": "zMZCynveT9o",
            "recommended": false,
            "updates": 0,
            "tags": null,
            "isFilm": false,
            "isDocumentry": false,
            "labels": "",
            "charge": 0,
            "vipResource": "1080P",
            "sNo": "",
            "serialCount": 0,
            "score": "暂无评分",
            "isFix": false
          },
          {
            "atypeName": "动漫",
            "videoClassID": "0,1,6,46",
            "image": "https://static.yfsp.tv/upload/video/202503261819051956844.gif",
            "key": "XIvOD16QqWE",
            "lang": "国语",
            "cid": "热血",
            "lastName": "12集全",
            "isShowTodayNum": false,
            "title": "画江湖之不良人第7季",
            "hot": 1029446,
            "rating": "9.0",
            "year": 2025,
            "regional": "大陆",
            "addTime": "2025年03月26日",
            "directed": "唐媛",
            "starring": "边江,申秋香",
            "shareCount": 199,
            "dd": 500,
            "dc": 57,
            "comments": 391,
            "favoriteCount": 1941,
            "contxt": "漠北当下表面平静，实则暗中涌动。王后述里朵正筹划一场大会，不良帅为探查漠北动向带着一众不良人出现在漠北，以降臣为首的四大尸祖在此期间也来到漠北开了家古董羹店，而神秘的杀人凶手更弄得人心惶惶，几方...",
            "isSerial": false,
            "updateweekly": "周四",
            "cidMapper": "热血",
            "lastKey": "GtHZ5xNnm70",
            "recommended": true,
            "updates": 0,
            "tags": null,
            "isFilm": false,
            "isDocumentry": false,
            "labels": "",
            "charge": 0,
            "vipResource": "4K",
            "sNo": "",
            "serialCount": 0,
            "score": "9.0",
            "isFix": false
          }
        ],
        "maxpage": 30,
        "fmdata": {
          "rate": 0,
          "fminfo": {}
        }
      }
    ]
  },
  "msg": ""
}